disclosurecheck/__init__.py
disclosurecheck/main.py
disclosurecheck/collectors/__init__.py
disclosurecheck/collectors/fallback.py
disclosurecheck/collectors/github.py
disclosurecheck/collectors/ibb.py
disclosurecheck/collectors/librariesio.py
disclosurecheck/collectors/npm.py
disclosurecheck/collectors/nuget.py
disclosurecheck/collectors/overrides.py
disclosurecheck/collectors/packagecontent.py
disclosurecheck/collectors/pypi.py
disclosurecheck/collectors/securityinsights.py
disclosurecheck/collectors/tidelift.py
disclosurecheck/overrides/__init__.py
disclosurecheck/overrides/gem/__init__.py
disclosurecheck/overrides/gem/rails.json
disclosurecheck/util/__init__.py
disclosurecheck/util/context.py
disclosurecheck/util/normalize.py
disclosurecheck/util/searchers.py
tests/disclosurecheck/__init__.py
tests/disclosurecheck/test_end_to_end.py
tests/disclosurecheck/test_sanitize_github_url.py
venv/bin/rst2html.py
venv/bin/rst2html4.py
venv/bin/rst2html5.py
venv/bin/rst2latex.py
venv/bin/rst2man.py
venv/bin/rst2odt.py
venv/bin/rst2odt_prepstyles.py
venv/bin/rst2pseudoxml.py
venv/bin/rst2s5.py
venv/bin/rst2xetex.py
venv/bin/rst2xml.py
venv/bin/rstpep2html.py
disclosurecheck-0.0.6.dist-info/LICENSE
disclosurecheck-0.0.6.dist-info/METADATA
disclosurecheck-0.0.6.dist-info/WHEEL
disclosurecheck-0.0.6.dist-info/entry_points.txt
disclosurecheck-0.0.6.dist-info/top_level.txt
disclosurecheck-0.0.6.dist-info/RECORD
