Metadata-Version: 2.1
Name: disclosurecheck
Version: 0.0.6
Summary: Discover methods for disclosing security vulnerabilities to a project privately.
Author-email: Michael Scovetta <michael.scovetta@gmail.com>
License: Apache License
Project-URL: Homepage, https://github.com/scovetta/disclosure-check
Project-URL: Bug Tracker, https://github.com/scovetta/disclosure-check/issues
Classifier: Development Status :: 4 - Beta
Classifier: Programming Language :: Python :: 3
Classifier: License :: OSI Approved :: Apache Software License
Classifier: Operating System :: OS Independent
Requires-Python: >=3.10
License-File: LICENSE
Requires-Dist: packageurl-python (>=0.11.1)
Requires-Dist: PyGithub (>=1.58.1)
Requires-Dist: requests (>=2.28.2)
Requires-Dist: requests-cache (>=1.0.1)
Requires-Dist: urllib3 (>=1.26.15)
Requires-Dist: urlextract
Requires-Dist: PyYAML (>=6.0)
Requires-Dist: rich
Requires-Dist: validators (>=0.20.0)
